CONTRIBUTING.txt
CONTRIBUTORS.txt
DEPENDS-docs.txt
DEPENDS.txt
LICENSE.txt
MANIFEST.in
Makefile
TASKS.txt
setup.cfg
setup.py
./skfuzzy/__init__.py
./skfuzzy/cluster/__init__.py
./skfuzzy/cluster/_cmeans.py
./skfuzzy/control/__init__.py
./skfuzzy/control/antecedent_consequent.py
./skfuzzy/control/controlsystem.py
./skfuzzy/control/fuzzyvariable.py
./skfuzzy/control/ordereddict.py
./skfuzzy/control/rule.py
./skfuzzy/control/state.py
./skfuzzy/control/term.py
./skfuzzy/control/visualization.py
./skfuzzy/defuzzify/__init__.py
./skfuzzy/defuzzify/defuzz.py
./skfuzzy/filters/__init__.py
./skfuzzy/filters/fire.py
./skfuzzy/fuzzymath/__init__.py
./skfuzzy/fuzzymath/_continuous_to_discrete.py
./skfuzzy/fuzzymath/fuzzy_logic.py
./skfuzzy/fuzzymath/fuzzy_ops.py
./skfuzzy/image/__init__.py
./skfuzzy/image/arraypad.py
./skfuzzy/image/astronaut_gray.npy
./skfuzzy/image/astronaut_rgb.npy
./skfuzzy/image/imops.py
./skfuzzy/image/metrics.py
./skfuzzy/image/shape.py
./skfuzzy/intervals/__init__.py
./skfuzzy/intervals/intervalops.py
./skfuzzy/membership/__init__.py
./skfuzzy/membership/generatemf.py
docs/Makefile
docs/examples/plot_cmeans.py
docs/examples/plot_control_system_advanced.py
docs/examples/plot_defuzzify.py
docs/examples/plot_tipping_problem.py
docs/examples/plot_tipping_problem_newapi.py
docs/ext/docscrape.py
docs/ext/docscrape_sphinx.py
docs/ext/numpydoc.py
docs/ext/plot2rst.py
docs/ext/plot_directive.py
docs/logo/skfuzzy_icon.py
docs/logo/skfuzzy_logo.py
docs/source/conf.py
docs/source/contribute.txt
docs/source/documentation.txt
docs/source/index.txt
docs/source/install.txt
docs/source/license.txt
docs/source/overview.txt
docs/source/random_gallery.py
docs/source/user_guide.txt
docs/source/_templates/localtoc.html
docs/source/_templates/navbar.html
docs/source/_templates/navigation.html
docs/source/api/api.txt
docs/source/api/skfuzzy.cluster.txt
docs/source/api/skfuzzy.control.txt
docs/source/api/skfuzzy.defuzzify.txt
docs/source/api/skfuzzy.filters.txt
scikit_fuzzy.egg-info/PKG-INFO
scikit_fuzzy.egg-info/SOURCES.txt
scikit_fuzzy.egg-info/dependency_links.txt
scikit_fuzzy.egg-info/not-zip-safe
scikit_fuzzy.egg-info/requires.txt
scikit_fuzzy.egg-info/top_level.txt
